fernet256/__init__.py
fernet256/main.py
fernet256-3.0.0.dist-info/licenses/LICENSE
fernet256-3.0.0.dist-info/METADATA
fernet256-3.0.0.dist-info/WHEEL
fernet256-3.0.0.dist-info/top_level.txt
fernet256-3.0.0.dist-info/RECORD
