Metadata-Version: 2.4
Name: fernet256
Version: 3.0.0
Summary: Simplified AES-256 encryption tool inspired by Fernet
Home-page: https://github.com/xRangeroQ/fernet256
Author: xRangeroQ
Requires-Python: >=3.9
License-File: LICENSE
Requires-Dist: pycryptodome>=3.23.0
Dynamic: author
Dynamic: description
Dynamic: description-content-type
Dynamic: home-page
Dynamic: license-file
Dynamic: requires-dist
Dynamic: requires-python
Dynamic: summary
